{"sensor_id":"temp_2","tipo":"temperatura","valor":34.56,"timestamp":1777567845,"event_time":"2026-04-30T11:50:45.000-05:00"}
{"sensor_id":"pres_2","tipo":"presion","valor":1039.98,"timestamp":1777567846,"event_time":"2026-04-30T11:50:46.000-05:00"}
{"sensor_id":"temp_1","tipo":"temperatura","valor":31.07,"timestamp":1777567846,"event_time":"2026-04-30T11:50:46.000-05:00"}
{"sensor_id":"temp_1","tipo":"temperatura","valor":38.84,"timestamp":1777567847,"event_time":"2026-04-30T11:50:47.000-05:00"}
{"sensor_id":"pres_2","tipo":"presion","valor":914.58,"timestamp":1777567848,"event_time":"2026-04-30T11:50:48.000-05:00"}
{"sensor_id":"temp_3","tipo":"temperatura","valor":37.51,"timestamp":1777567848,"event_time":"2026-04-30T11:50:48.000-05:00"}
{"sensor_id":"temp_1","tipo":"temperatura","valor":62.35,"timestamp":1777567849,"event_time":"2026-04-30T11:50:49.000-05:00"}
{"sensor_id":"pres_1","tipo":"presion","valor":963.66,"timestamp":1777567850,"event_time":"2026-04-30T11:50:50.000-05:00"}
