{"sensor_id":"temp_3","tipo":"temperatura","valor":66.42,"timestamp":1777573270,"event_time":"2026-04-30T13:21:10.000-05:00"}
{"sensor_id":"pres_3","tipo":"presion","valor":1079.3,"timestamp":1777573271,"event_time":"2026-04-30T13:21:11.000-05:00"}
{"sensor_id":"temp_1","tipo":"temperatura","valor":40.63,"timestamp":1777573271,"event_time":"2026-04-30T13:21:11.000-05:00"}
{"sensor_id":"temp_3","tipo":"temperatura","valor":85.35,"timestamp":1777573272,"event_time":"2026-04-30T13:21:12.000-05:00"}
{"sensor_id":"pres_1","tipo":"presion","valor":1002.2,"timestamp":1777573273,"event_time":"2026-04-30T13:21:13.000-05:00"}
{"sensor_id":"temp_2","tipo":"temperatura","valor":62.11,"timestamp":1777573273,"event_time":"2026-04-30T13:21:13.000-05:00"}
{"sensor_id":"temp_3","tipo":"temperatura","valor":46.19,"timestamp":1777573274,"event_time":"2026-04-30T13:21:14.000-05:00"}
